{
  "actions" : [ {
    "module" : "init",
    "date" : "2025-01-17T18:59:12.047603877Z",
    "properties" : {
      "packageName" : "com.mycompany.myapp",
      "projectName" : "JHipster Sample Application",
      "baseName" : "jhipsterSampleApplication",
      "endOfLine" : "lf",
      "indentSize" : 2
    }
  }, {
    "module" : "application-service-hexagonal-architecture-documentation",
    "date" : "2025-01-17T18:59:12.117757094Z",
    "properties" : {
      "packageName" : "com.mycompany.myapp",
      "projectName" : "JHipster Sample Application",
      "baseName" : "jhipsterSampleApplication",
      "endOfLine" : "lf",
      "indentSize" : 2
    }
  }, {
    "module" : "maven-java",
    "date" : "2025-01-17T18:59:12.340658631Z",
    "properties" : {
      "packageName" : "com.mycompany.myapp",
      "projectName" : "JHipster Sample Application",
      "baseName" : "jhipsterSampleApplication",
      "endOfLine" : "lf",
      "indentSize" : 2
    }
  }, {
    "module" : "prettier",
    "date" : "2025-01-17T18:59:12.417960271Z",
    "properties" : {
      "packageName" : "com.mycompany.myapp",
      "projectName" : "JHipster Sample Application",
      "baseName" : "jhipsterSampleApplication",
      "endOfLine" : "lf",
      "indentSize" : 2
    }
  }, {
    "module" : "checkstyle",
    "date" : "2025-01-17T18:59:12.500277056Z",
    "properties" : {
      "packageName" : "com.mycompany.myapp",
      "projectName" : "JHipster Sample Application",
      "baseName" : "jhipsterSampleApplication",
      "endOfLine" : "lf",
      "indentSize" : 2
    }
  }, {
    "module" : "jacoco-with-min-coverage-check",
    "date" : "2025-01-17T18:59:12.604299839Z",
    "properties" : {
      "packageName" : "com.mycompany.myapp",
      "projectName" : "JHipster Sample Application",
      "baseName" : "jhipsterSampleApplication",
      "endOfLine" : "lf",
      "indentSize" : 2
    }
  }, {
    "module" : "java-base",
    "date" : "2025-01-17T18:59:12.727999804Z",
    "properties" : {
      "packageName" : "com.mycompany.myapp",
      "projectName" : "JHipster Sample Application",
      "baseName" : "jhipsterSampleApplication",
      "endOfLine" : "lf",
      "indentSize" : 2
    }
  }, {
    "module" : "maven-wrapper",
    "date" : "2025-01-17T18:59:12.798563627Z",
    "properties" : {
      "packageName" : "com.mycompany.myapp",
      "projectName" : "JHipster Sample Application",
      "baseName" : "jhipsterSampleApplication",
      "endOfLine" : "lf",
      "indentSize" : 2
    }
  }, {
    "module" : "init",
    "date" : "2025-01-17T18:59:24.008050935Z",
    "properties" : {
      "packageName" : "com.mycompany.myapp",
      "projectName" : "JHipster Sample Application",
      "baseName" : "jhipsterSampleApplication",
      "endOfLine" : "lf",
      "indentSize" : 2,
      "serverPort" : 8080,
      "springConfigurationFormat" : "yaml"
    }
  }, {
    "module" : "application-service-hexagonal-architecture-documentation",
    "date" : "2025-01-17T18:59:24.118500001Z",
    "properties" : {
      "packageName" : "com.mycompany.myapp",
      "projectName" : "JHipster Sample Application",
      "baseName" : "jhipsterSampleApplication",
      "endOfLine" : "lf",
      "indentSize" : 2,
      "serverPort" : 8080,
      "springConfigurationFormat" : "yaml"
    }
  }, {
    "module" : "maven-java",
    "date" : "2025-01-17T18:59:24.243194805Z",
    "properties" : {
      "packageName" : "com.mycompany.myapp",
      "projectName" : "JHipster Sample Application",
      "baseName" : "jhipsterSampleApplication",
      "endOfLine" : "lf",
      "indentSize" : 2,
      "serverPort" : 8080,
      "springConfigurationFormat" : "yaml"
    }
  }, {
    "module" : "prettier",
    "date" : "2025-01-17T18:59:24.348620385Z",
    "properties" : {
      "packageName" : "com.mycompany.myapp",
      "projectName" : "JHipster Sample Application",
      "baseName" : "jhipsterSampleApplication",
      "endOfLine" : "lf",
      "indentSize" : 2,
      "serverPort" : 8080,
      "springConfigurationFormat" : "yaml"
    }
  }, {
    "module" : "typescript",
    "date" : "2025-01-17T18:59:24.459997859Z",
    "properties" : {
      "packageName" : "com.mycompany.myapp",
      "projectName" : "JHipster Sample Application",
      "baseName" : "jhipsterSampleApplication",
      "endOfLine" : "lf",
      "indentSize" : 2,
      "serverPort" : 8080,
      "springConfigurationFormat" : "yaml"
    }
  }, {
    "module" : "checkstyle",
    "date" : "2025-01-17T18:59:24.573433309Z",
    "properties" : {
      "packageName" : "com.mycompany.myapp",
      "projectName" : "JHipster Sample Application",
      "baseName" : "jhipsterSampleApplication",
      "endOfLine" : "lf",
      "indentSize" : 2,
      "serverPort" : 8080,
      "springConfigurationFormat" : "yaml"
    }
  }, {
    "module" : "jacoco-with-min-coverage-check",
    "date" : "2025-01-17T18:59:24.695150658Z",
    "properties" : {
      "packageName" : "com.mycompany.myapp",
      "projectName" : "JHipster Sample Application",
      "baseName" : "jhipsterSampleApplication",
      "endOfLine" : "lf",
      "indentSize" : 2,
      "serverPort" : 8080,
      "springConfigurationFormat" : "yaml"
    }
  }, {
    "module" : "java-base",
    "date" : "2025-01-17T18:59:24.894016932Z",
    "properties" : {
      "packageName" : "com.mycompany.myapp",
      "projectName" : "JHipster Sample Application",
      "baseName" : "jhipsterSampleApplication",
      "endOfLine" : "lf",
      "indentSize" : 2,
      "serverPort" : 8080,
      "springConfigurationFormat" : "yaml"
    }
  }, {
    "module" : "maven-wrapper",
    "date" : "2025-01-17T18:59:25.002691900Z",
    "properties" : {
      "packageName" : "com.mycompany.myapp",
      "projectName" : "JHipster Sample Application",
      "baseName" : "jhipsterSampleApplication",
      "endOfLine" : "lf",
      "indentSize" : 2,
      "serverPort" : 8080,
      "springConfigurationFormat" : "yaml"
    }
  }, {
    "module" : "vue-core",
    "date" : "2025-01-17T18:59:25.139068151Z",
    "properties" : {
      "packageName" : "com.mycompany.myapp",
      "projectName" : "JHipster Sample Application",
      "baseName" : "jhipsterSampleApplication",
      "endOfLine" : "lf",
      "indentSize" : 2,
      "serverPort" : 8080,
      "springConfigurationFormat" : "yaml"
    }
  } ]
}